{
    "status": "succeeded",
    "createdDateTime": "2020-10-11T07:55:50Z",
    "lastUpdatedDateTime": "2020-10-11T07:55:50Z",
    "analyzeResult": {
        "version": "3.0.0",
        "readResults": [
            {
                "page": 1,
                "language": "en",
                "angle": -1.6766,
                "width": 1653,
                "height": 2339,
                "unit": "pixel",
                "lines": [
                    {
                        "boundingBox": [
                            102,
                            131,
                            874,
                            89,
                            878,
                            153,
                            102,
                            185
                        ],
                        "text": "Software took to check Saw Hearts.",
                        "words": [
                            {
                                "boundingBox": [
                                    104,
                                    135,
                                    299,
                                    127,
                                    298,
                                    182,
                                    102,
                                    185
                                ],
                                "text": "Software",
                                "confidence": 0.559
                            },
                            {
                                "boundingBox": [
                                    329,
                                    125,
                                    409,
                                    121,
                                    409,
                                    179,
                                    328,
                                    182
                                ],
                                "text": "took",
                                "confidence": 0.786
                            },
                            {
                                "boundingBox": [
                                    419,
                                    121,
                                    479,
                                    117,
                                    480,
                                    175,
                                    419,
                                    178
                                ],
                                "text": "to",
                                "confidence": 0.983
                            },
                            {
                                "boundingBox": [
                                    489,
                                    117,
                                    606,
                                    109,
                                    608,
                                    168,
                                    490,
                                    175
                                ],
                                "text": "check",
                                "confidence": 0.635
                            },
                            {
                                "boundingBox": [
                                    636,
                                    107,
                                    743,
                                    100,
                                    746,
                                    159,
                                    638,
                                    166
                                ],
                                "text": "Saw",
                                "confidence": 0.819
                            },
                            {
                                "boundingBox": [
                                    770,
                                    98,
                                    874,
                                    90,
                                    877,
                                    147,
                                    773,
                                    156
                                ],
                                "text": "Hearts.",
                                "confidence": 0.568
                            }
                        ]
                    },
                    {
                        "boundingBox": [
                            181,
                            231,
                            616,
                            222,
                            617,
                            282,
                            182,
                            288
                        ],
                        "text": "saas provided toode :",
                        "words": [
                            {
                                "boundingBox": [
                                    187,
                                    232,
                                    300,
                                    231,
                                    299,
                                    288,
                                    185,
                                    286
                                ],
                                "text": "saas",
                                "confidence": 0.764
                            },
                            {
                                "boundingBox": [
                                    314,
                                    231,
                                    487,
                                    227,
                                    486,
                                    286,
                                    313,
                                    288
                                ],
                                "text": "provided",
                                "confidence": 0.559
                            },
                            {
                                "boundingBox": [
                                    504,
                                    226,
                                    575,
                                    224,
                                    575,
                                    282,
                                    504,
                                    285
                                ],
                                "text": "toode",
                                "confidence": 0.563
                            },
                            {
                                "boundingBox": [
                                    586,
                                    224,
                                    617,
                                    223,
                                    617,
                                    279,
                                    585,
                                    281
                                ],
                                "text": ":",
                                "confidence": 0.614
                            }
                        ]
                    },
                    {
                        "boundingBox": [
                            212,
                            333,
                            1550,
                            245,
                            1551,
                            308,
                            215,
                            386
                        ],
                        "text": "Sometimes saas provide tool that shows the he heach a",
                        "words": [
                            {
                                "boundingBox": [
                                    219,
                                    339,
                                    387,
                                    328,
                                    388,
                                    379,
                                    221,
                                    386
                                ],
                                "text": "Sometimes",
                                "confidence": 0.559
                            },
                            {
                                "boundingBox": [
                                    424,
                                    325,
                                    522,
                                    319,
                                    523,
                                    373,
                                    425,
                                    378
                                ],
                                "text": "saas",
                                "confidence": 0.827
                            },
                            {
                                "boundingBox": [
                                    534,
                                    318,
                                    687,
                                    307,
                                    687,
                                    365,
                                    535,
                                    372
                                ],
                                "text": "provide",
                                "confidence": 0.642
                            },
                            {
                                "boundingBox": [
                                    721,
                                    305,
                                    809,
                                    299,
                                    809,
                                    358,
                                    721,
                                    363
                                ],
                                "text": "tool",
                                "confidence": 0.559
                            },
                            {
                                "boundingBox": [
                                    849,
                                    296,
                                    944,
                                    289,
                                    943,
                                    350,
                                    849,
                                    355
                                ],
                                "text": "that",
                                "confidence": 0.715
                            },
                            {
                                "boundingBox": [
                                    987,
                                    286,
                                    1100,
                                    278,
                                    1099,
                                    340,
                                    986,
                                    347
                                ],
                                "text": "shows",
                                "confidence": 0.903
                            },
                            {
                                "boundingBox": [
                                    1109,
                                    277,
                                    1189,
                                    272,
                                    1187,
                                    334,
                                    1108,
                                    339
                                ],
                                "text": "the",
                                "confidence": 0.833
                            },
                            {
                                "boundingBox": [
                                    1250,
                                    267,
                                    1317,
                                    262,
                                    1315,
                                    324,
                                    1248,
                                    329
                                ],
                                "text": "he",
                                "confidence": 0.559
                            },
                            {
                                "boundingBox": [
                                    1354,
                                    260,
                                    1483,
                                    250,
                                    1480,
                                    311,
                                    1352,
                                    322
                                ],
                                "text": "heach",
                                "confidence": 0.559
                            },
                            {
                                "boundingBox": [
                                    1526,
                                    247,
                                    1550,
                                    245,
                                    1547,
                                    306,
                                    1523,
                                    308
                                ],
                                "text": "a",
                                "confidence": 0.613
                            }
                        ]
                    },
                    {
                        "boundingBox": [
                            232,
                            419,
                            1513,
                            335,
                            1516,
                            398,
                            234,
                            474
                        ],
                        "text": "Saas Service, they imforam alout upcoming outages and",
                        "words": [
                            {
                                "boundingBox": [
                                    236,
                                    419,
                                    348,
                                    413,
                                    349,
                                    470,
                                    237,
                                    474
                                ],
                                "text": "Saas",
                                "confidence": 0.712
                            },
                            {
                                "boundingBox": [
                                    366,
                                    412,
                                    517,
                                    404,
                                    518,
                                    463,
                                    367,
                                    469
                                ],
                                "text": "Service,",
                                "confidence": 0.69
                            },
                            {
                                "boundingBox": [
                                    532,
                                    403,
                                    629,
                                    397,
                                    630,
                                    457,
                                    533,
                                    462
                                ],
                                "text": "they",
                                "confidence": 0.645
                            },
                            {
                                "boundingBox": [
                                    640,
                                    397,
                                    798,
                                    387,
                                    799,
                                    447,
                                    641,
                                    456
                                ],
                                "text": "imforam",
                                "confidence": 0.559
                            },
                            {
                                "boundingBox": [
                                    830,
                                    385,
                                    946,
                                    377,
                                    947,
                                    437,
                                    832,
                                    445
                                ],
                                "text": "alout",
                                "confidence": 0.652
                            },
                            {
                                "boundingBox": [
                                    1007,
                                    373,
                                    1205,
                                    359,
                                    1206,
                                    417,
                                    1008,
                                    433
                                ],
                                "text": "upcoming",
                                "confidence": 0.796
                            },
                            {
                                "boundingBox": [
                                    1244,
                                    356,
                                    1406,
                                    344,
                                    1408,
                                    398,
                                    1246,
                                    413
                                ],
                                "text": "outages",
                                "confidence": 0.823
                            },
                            {
                                "boundingBox": [
                                    1442,
                                    341,
                                    1514,
                                    335,
                                    1516,
                                    387,
                                    1444,
                                    395
                                ],
                                "text": "and",
                                "confidence": 0.981
                            }
                        ]
                    },
                    {
                        "boundingBox": [
                            216,
                            515,
                            597,
                            493,
                            600,
                            552,
                            218,
                            566
                        ],
                        "text": "maintainme dates ?",
                        "words": [
                            {
                                "boundingBox": [
                                    229,
                                    516,
                                    417,
                                    513,
                                    419,
                                    564,
                                    231,
                                    566
                                ],
                                "text": "maintainme",
                                "confidence": 0.652
                            },
                            {
                                "boundingBox": [
                                    472,
                                    508,
                                    558,
                                    498,
                                    561,
                                    550,
                                    474,
                                    560
                                ],
                                "text": "dates",
                                "confidence": 0.829
                            },
                            {
                                "boundingBox": [
                                    568,
                                    497,
                                    597,
                                    493,
                                    599,
                                    544,
                                    570,
                                    548
                                ],
                                "text": "?",
                                "confidence": 0.559
                            }
                        ]
                    },
                    {
                        "boundingBox": [
                            244,
                            567,
                            671,
                            561,
                            672,
                            634,
                            244,
                            635
                        ],
                        "text": "So User can get to",
                        "words": [
                            {
                                "boundingBox": [
                                    244,
                                    584,
                                    303,
                                    586,
                                    304,
                                    627,
                                    244,
                                    625
                                ],
                                "text": "So",
                                "confidence": 0.986
                            },
                            {
                                "boundingBox": [
                                    338,
                                    587,
                                    416,
                                    586,
                                    417,
                                    630,
                                    339,
                                    628
                                ],
                                "text": "User",
                                "confidence": 0.885
                            },
                            {
                                "boundingBox": [
                                    448,
                                    584,
                                    526,
                                    579,
                                    528,
                                    633,
                                    450,
                                    631
                                ],
                                "text": "can",
                                "confidence": 0.979
                            },
                            {
                                "boundingBox": [
                                    577,
                                    573,
                                    635,
                                    566,
                                    639,
                                    635,
                                    579,
                                    634
                                ],
                                "text": "get",
                                "confidence": 0.979
                            },
                            {
                                "boundingBox": [
                                    643,
                                    565,
                                    670,
                                    561,
                                    673,
                                    635,
                                    647,
                                    635
                                ],
                                "text": "to",
                                "confidence": 0.754
                            }
                        ]
                    },
                    {
                        "boundingBox": [
                            703,
                            554,
                            1515,
                            511,
                            1518,
                            588,
                            703,
                            631
                        ],
                        "text": "know about Saas Reach from Rever",
                        "words": [
                            {
                                "boundingBox": [
                                    713,
                                    555,
                                    844,
                                    547,
                                    845,
                                    624,
                                    714,
                                    631
                                ],
                                "text": "know",
                                "confidence": 0.635
                            },
                            {
                                "boundingBox": [
                                    859,
                                    546,
                                    1004,
                                    538,
                                    1005,
                                    614,
                                    860,
                                    623
                                ],
                                "text": "about",
                                "confidence": 0.588
                            },
                            {
                                "boundingBox": [
                                    1019,
                                    537,
                                    1140,
                                    531,
                                    1141,
                                    607,
                                    1020,
                                    614
                                ],
                                "text": "Saas",
                                "confidence": 0.944
                            },
                            {
                                "boundingBox": [
                                    1155,
                                    530,
                                    1281,
                                    523,
                                    1282,
                                    600,
                                    1156,
                                    606
                                ],
                                "text": "Reach",
                                "confidence": 0.559
                            },
                            {
                                "boundingBox": [
                                    1296,
                                    523,
                                    1411,
                                    517,
                                    1413,
                                    594,
                                    1297,
                                    600
                                ],
                                "text": "from",
                                "confidence": 0.559
                            },
                            {
                                "boundingBox": [
                                    1426,
                                    516,
                                    1517,
                                    512,
                                    1518,
                                    590,
                                    1428,
                                    594
                                ],
                                "text": "Rever",
                                "confidence": 0.631
                            }
                        ]
                    },
                    {
                        "boundingBox": [
                            184,
                            686,
                            833,
                            671,
                            835,
                            724,
                            185,
                            735
                        ],
                        "text": "Cloud computing Ancidents Database :",
                        "words": [
                            {
                                "boundingBox": [
                                    191,
                                    687,
                                    310,
                                    687,
                                    310,
                                    735,
                                    191,
                                    735
                                ],
                                "text": "Cloud",
                                "confidence": 0.825
                            },
                            {
                                "boundingBox": [
                                    335,
                                    686,
                                    506,
                                    684,
                                    506,
                                    733,
                                    335,
                                    735
                                ],
                                "text": "computing",
                                "confidence": 0.652
                            },
                            {
                                "boundingBox": [
                                    534,
                                    683,
                                    684,
                                    678,
                                    684,
                                    727,
                                    534,
                                    732
                                ],
                                "text": "Ancidents",
                                "confidence": 0.64
                            },
                            {
                                "boundingBox": [
                                    693,
                                    678,
                                    799,
                                    673,
                                    799,
                                    722,
                                    693,
                                    727
                                ],
                                "text": "Database",
                                "confidence": 0.616
                            },
                            {
                                "boundingBox": [
                                    809,
                                    672,
                                    833,
                                    671,
                                    834,
                                    720,
                                    809,
                                    721
                                ],
                                "text": ":",
                                "confidence": 0.893
                            }
                        ]
                    },
                    {
                        "boundingBox": [
                            262,
                            763,
                            1508,
                            725,
                            1510,
                            778,
                            262,
                            813
                        ],
                        "text": "Of boks track of incidents and outags of major JP.",
                        "words": [
                            {
                                "boundingBox": [
                                    263,
                                    764,
                                    324,
                                    762,
                                    324,
                                    812,
                                    263,
                                    813
                                ],
                                "text": "Of",
                                "confidence": 0.755
                            },
                            {
                                "boundingBox": [
                                    363,
                                    761,
                                    464,
                                    758,
                                    464,
                                    809,
                                    363,
                                    812
                                ],
                                "text": "boks",
                                "confidence": 0.559
                            },
                            {
                                "boundingBox": [
                                    474,
                                    757,
                                    587,
                                    754,
                                    588,
                                    806,
                                    474,
                                    809
                                ],
                                "text": "track",
                                "confidence": 0.559
                            },
                            {
                                "boundingBox": [
                                    610,
                                    753,
                                    672,
                                    751,
                                    672,
                                    804,
                                    611,
                                    806
                                ],
                                "text": "of",
                                "confidence": 0.947
                            },
                            {
                                "boundingBox": [
                                    695,
                                    750,
                                    854,
                                    745,
                                    854,
                                    799,
                                    695,
                                    803
                                ],
                                "text": "incidents",
                                "confidence": 0.564
                            },
                            {
                                "boundingBox": [
                                    876,
                                    745,
                                    961,
                                    742,
                                    962,
                                    796,
                                    877,
                                    798
                                ],
                                "text": "and",
                                "confidence": 0.98
                            },
                            {
                                "boundingBox": [
                                    1006,
                                    741,
                                    1159,
                                    736,
                                    1160,
                                    790,
                                    1007,
                                    794
                                ],
                                "text": "outags",
                                "confidence": 0.652
                            },
                            {
                                "boundingBox": [
                                    1178,
                                    736,
                                    1240,
                                    734,
                                    1241,
                                    787,
                                    1179,
                                    789
                                ],
                                "text": "of",
                                "confidence": 0.958
                            },
                            {
                                "boundingBox": [
                                    1269,
                                    733,
                                    1383,
                                    730,
                                    1384,
                                    782,
                                    1271,
                                    786
                                ],
                                "text": "major",
                                "confidence": 0.652
                            },
                            {
                                "boundingBox": [
                                    1448,
                                    728,
                                    1510,
                                    726,
                                    1511,
                                    777,
                                    1449,
                                    779
                                ],
                                "text": "JP.",
                                "confidence": 0.564
                            }
                        ]
                    },
                    {
                        "boundingBox": [
                            241,
                            857,
                            990,
                            831,
                            992,
                            883,
                            242,
                            903
                        ],
                        "text": "So Use can get to know about it's",
                        "words": [
                            {
                                "boundingBox": [
                                    248,
                                    862,
                                    306,
                                    860,
                                    303,
                                    903,
                                    245,
                                    903
                                ],
                                "text": "So",
                                "confidence": 0.985
                            },
                            {
                                "boundingBox": [
                                    347,
                                    858,
                                    416,
                                    856,
                                    414,
                                    902,
                                    345,
                                    903
                                ],
                                "text": "Use",
                                "confidence": 0.559
                            },
                            {
                                "boundingBox": [
                                    433,
                                    855,
                                    510,
                                    852,
                                    508,
                                    900,
                                    431,
                                    901
                                ],
                                "text": "can",
                                "confidence": 0.981
                            },
                            {
                                "boundingBox": [
                                    543,
                                    851,
                                    598,
                                    849,
                                    597,
                                    898,
                                    542,
                                    899
                                ],
                                "text": "get",
                                "confidence": 0.786
                            },
                            {
                                "boundingBox": [
                                    606,
                                    849,
                                    661,
                                    846,
                                    661,
                                    896,
                                    605,
                                    898
                                ],
                                "text": "to",
                                "confidence": 0.98
                            },
                            {
                                "boundingBox": [
                                    683,
                                    845,
                                    777,
                                    841,
                                    778,
                                    892,
                                    683,
                                    895
                                ],
                                "text": "know",
                                "confidence": 0.69
                            },
                            {
                                "boundingBox": [
                                    802,
                                    840,
                                    901,
                                    836,
                                    902,
                                    887,
                                    802,
                                    891
                                ],
                                "text": "about",
                                "confidence": 0.652
                            },
                            {
                                "boundingBox": [
                                    918,
                                    835,
                                    989,
                                    831,
                                    991,
                                    882,
                                    919,
                                    886
                                ],
                                "text": "it's",
                                "confidence": 0.96
                            }
                        ]
                    },
                    {
                        "boundingBox": [
                            1078,
                            823,
                            1429,
                            809,
                            1431,
                            870,
                            1079,
                            884
                        ],
                        "text": "CSP loom here.",
                        "words": [
                            {
                                "boundingBox": [
                                    1079,
                                    823,
                                    1167,
                                    820,
                                    1168,
                                    880,
                                    1079,
                                    884
                                ],
                                "text": "CSP",
                                "confidence": 0.981
                            },
                            {
                                "boundingBox": [
                                    1179,
                                    820,
                                    1312,
                                    814,
                                    1313,
                                    874,
                                    1180,
                                    879
                                ],
                                "text": "loom",
                                "confidence": 0.789
                            },
                            {
                                "boundingBox": [
                                    1328,
                                    814,
                                    1429,
                                    810,
                                    1430,
                                    871,
                                    1329,
                                    873
                                ],
                                "text": "here.",
                                "confidence": 0.582
                            }
                        ]
                    },
                    {
                        "boundingBox": [
                            225,
                            957,
                            648,
                            957,
                            648,
                            1015,
                            225,
                            1015
                        ],
                        "text": "Third party software ,",
                        "words": [
                            {
                                "boundingBox": [
                                    231,
                                    963,
                                    341,
                                    960,
                                    342,
                                    1014,
                                    233,
                                    1009
                                ],
                                "text": "Third",
                                "confidence": 0.559
                            },
                            {
                                "boundingBox": [
                                    376,
                                    959,
                                    471,
                                    958,
                                    473,
                                    1016,
                                    378,
                                    1015
                                ],
                                "text": "party",
                                "confidence": 0.643
                            },
                            {
                                "boundingBox": [
                                    497,
                                    958,
                                    612,
                                    958,
                                    615,
                                    1013,
                                    500,
                                    1016
                                ],
                                "text": "software",
                                "confidence": 0.559
                            },
                            {
                                "boundingBox": [
                                    621,
                                    958,
                                    645,
                                    958,
                                    648,
                                    1012,
                                    624,
                                    1013
                                ],
                                "text": ",",
                                "confidence": 0.559
                            }
                        ]
                    },
                    {
                        "boundingBox": [
                            230,
                            1038,
                            1491,
                            1038,
                            1491,
                            1100,
                            230,
                            1095
                        ],
                        "text": "There are third party software that provide freee health",
                        "words": [
                            {
                                "boundingBox": [
                                    242,
                                    1039,
                                    345,
                                    1039,
                                    347,
                                    1089,
                                    244,
                                    1085
                                ],
                                "text": "There",
                                "confidence": 0.622
                            },
                            {
                                "boundingBox": [
                                    354,
                                    1039,
                                    430,
                                    1039,
                                    432,
                                    1091,
                                    356,
                                    1089
                                ],
                                "text": "are",
                                "confidence": 0.708
                            },
                            {
                                "boundingBox": [
                                    448,
                                    1039,
                                    554,
                                    1040,
                                    556,
                                    1094,
                                    450,
                                    1092
                                ],
                                "text": "third",
                                "confidence": 0.768
                            },
                            {
                                "boundingBox": [
                                    566,
                                    1040,
                                    660,
                                    1040,
                                    662,
                                    1097,
                                    568,
                                    1095
                                ],
                                "text": "party",
                                "confidence": 0.559
                            },
                            {
                                "boundingBox": [
                                    693,
                                    1040,
                                    851,
                                    1040,
                                    853,
                                    1099,
                                    696,
                                    1097
                                ],
                                "text": "software",
                                "confidence": 0.565
                            },
                            {
                                "boundingBox": [
                                    881,
                                    1040,
                                    975,
                                    1040,
                                    977,
                                    1100,
                                    883,
                                    1100
                                ],
                                "text": "that",
                                "confidence": 0.559
                            },
                            {
                                "boundingBox": [
                                    1017,
                                    1040,
                                    1172,
                                    1040,
                                    1174,
                                    1100,
                                    1020,
                                    1100
                                ],
                                "text": "provide",
                                "confidence": 0.559
                            },
                            {
                                "boundingBox": [
                                    1211,
                                    1040,
                                    1317,
                                    1039,
                                    1320,
                                    1100,
                                    1214,
                                    1100
                                ],
                                "text": "freee",
                                "confidence": 0.561
                            },
                            {
                                "boundingBox": [
                                    1381,
                                    1039,
                                    1490,
                                    1039,
                                    1492,
                                    1098,
                                    1383,
                                    1099
                                ],
                                "text": "health",
                                "confidence": 0.845
                            }
                        ]
                    },
                    {
                        "boundingBox": [
                            241,
                            1123,
                            783,
                            1118,
                            784,
                            1172,
                            242,
                            1182
                        ],
                        "text": "Checking Desaas service.",
                        "words": [
                            {
                                "boundingBox": [
                                    242,
                                    1128,
                                    406,
                                    1121,
                                    407,
                                    1180,
                                    243,
                                    1183
                                ],
                                "text": "Checking",
                                "confidence": 0.568
                            },
                            {
                                "boundingBox": [
                                    442,
                                    1120,
                                    614,
                                    1119,
                                    616,
                                    1175,
                                    444,
                                    1180
                                ],
                                "text": "Desaas",
                                "confidence": 0.559
                            },
                            {
                                "boundingBox": [
                                    647,
                                    1119,
                                    782,
                                    1121,
                                    784,
                                    1171,
                                    649,
                                    1174
                                ],
                                "text": "service.",
                                "confidence": 0.559
                            }
                        ]
                    },
                    {
                        "boundingBox": [
                            245,
                            1219,
                            319,
                            1215,
                            320,
                            1267,
                            250,
                            1270
                        ],
                        "text": "Eur",
                        "words": [
                            {
                                "boundingBox": [
                                    248,
                                    1218,
                                    317,
                                    1215,
                                    320,
                                    1266,
                                    250,
                                    1270
                                ],
                                "text": "Eur",
                                "confidence": 0.559
                            }
                        ]
                    },
                    {
                        "boundingBox": [
                            346,
                            1206,
                            550,
                            1205,
                            553,
                            1259,
                            348,
                            1267
                        ],
                        "text": "Nagios .",
                        "words": [
                            {
                                "boundingBox": [
                                    419,
                                    1208,
                                    509,
                                    1206,
                                    511,
                                    1257,
                                    422,
                                    1264
                                ],
                                "text": "Nagios",
                                "confidence": 0.652
                            },
                            {
                                "boundingBox": [
                                    521,
                                    1206,
                                    550,
                                    1205,
                                    551,
                                    1254,
                                    523,
                                    1256
                                ],
                                "text": ".",
                                "confidence": 0.948
                            }
                        ]
                    },
                    {
                        "boundingBox": [
                            1064,
                            2272,
                            1498,
                            2272,
                            1498,
                            2308,
                            1064,
                            2308
                        ],
                        "text": "Scanned with CamScanner",
                        "words": [
                            {
                                "boundingBox": [
                                    1065,
                                    2273,
                                    1203,
                                    2273,
                                    1204,
                                    2308,
                                    1067,
                                    2309
                                ],
                                "text": "Scanned",
                                "confidence": 0.985
                            },
                            {
                                "boundingBox": [
                                    1210,
                                    2273,
                                    1279,
                                    2273,
                                    1279,
                                    2308,
                                    1211,
                                    2308
                                ],
                                "text": "with",
                                "confidence": 0.987
                            },
                            {
                                "boundingBox": [
                                    1286,
                                    2273,
                                    1497,
                                    2273,
                                    1497,
                                    2308,
                                    1286,
                                    2308
                                ],
                                "text": "CamScanner",
                                "confidence": 0.981
                            }
                        ]
                    }
                ]
            }
        ]
    }
}