{
    "status": "succeeded",
    "createdDateTime": "2020-10-11T09:14:01Z",
    "lastUpdatedDateTime": "2020-10-11T09:14:02Z",
    "analyzeResult": {
        "version": "3.0.0",
        "readResults": [
            {
                "page": 1,
                "language": "en",
                "angle": -0.1121,
                "width": 2339,
                "height": 1653,
                "unit": "pixel",
                "lines": [
                    {
                        "boundingBox": [
                            100,
                            320,
                            307,
                            322,
                            310,
                            385,
                            101,
                            390
                        ],
                        "text": "As - 4",
                        "words": [
                            {
                                "boundingBox": [
                                    127,
                                    320,
                                    183,
                                    320,
                                    184,
                                    389,
                                    128,
                                    390
                                ],
                                "text": "As",
                                "confidence": 0.652
                            },
                            {
                                "boundingBox": [
                                    197,
                                    320,
                                    258,
                                    320,
                                    259,
                                    389,
                                    198,
                                    389
                                ],
                                "text": "-",
                                "confidence": 0.985
                            },
                            {
                                "boundingBox": [
                                    272,
                                    320,
                                    309,
                                    320,
                                    310,
                                    389,
                                    273,
                                    389
                                ],
                                "text": "4",
                                "confidence": 0.986
                            }
                        ]
                    },
                    {
                        "boundingBox": [
                            309,
                            445,
                            2174,
                            458,
                            2173,
                            555,
                            309,
                            532
                        ],
                        "text": "There can be many steps involved in keeping",
                        "words": [
                            {
                                "boundingBox": [
                                    345,
                                    453,
                                    573,
                                    448,
                                    572,
                                    526,
                                    344,
                                    530
                                ],
                                "text": "There",
                                "confidence": 0.973
                            },
                            {
                                "boundingBox": [
                                    608,
                                    448,
                                    765,
                                    446,
                                    763,
                                    525,
                                    607,
                                    526
                                ],
                                "text": "can",
                                "confidence": 0.986
                            },
                            {
                                "boundingBox": [
                                    790,
                                    446,
                                    897,
                                    446,
                                    895,
                                    524,
                                    789,
                                    524
                                ],
                                "text": "be",
                                "confidence": 0.986
                            },
                            {
                                "boundingBox": [
                                    958,
                                    446,
                                    1150,
                                    446,
                                    1147,
                                    525,
                                    955,
                                    524
                                ],
                                "text": "many",
                                "confidence": 0.985
                            },
                            {
                                "boundingBox": [
                                    1201,
                                    447,
                                    1403,
                                    449,
                                    1400,
                                    529,
                                    1198,
                                    526
                                ],
                                "text": "steps",
                                "confidence": 0.768
                            },
                            {
                                "boundingBox": [
                                    1434,
                                    450,
                                    1753,
                                    458,
                                    1748,
                                    539,
                                    1430,
                                    530
                                ],
                                "text": "involved",
                                "confidence": 0.885
                            },
                            {
                                "boundingBox": [
                                    1788,
                                    459,
                                    1905,
                                    463,
                                    1899,
                                    544,
                                    1783,
                                    540
                                ],
                                "text": "in",
                                "confidence": 0.982
                            },
                            {
                                "boundingBox": [
                                    1930,
                                    464,
                                    2173,
                                    475,
                                    2167,
                                    556,
                                    1925,
                                    545
                                ],
                                "text": "keeping",
                                "confidence": 0.963
                            }
                        ]
                    },
                    {
                        "boundingBox": [
                            375,
                            551,
                            2162,
                            557,
                            2162,
                            625,
                            375,
                            617
                        ],
                        "text": "the data safe of ensuring storage of data is not",
                        "words": [
                            {
                                "boundingBox": [
                                    392,
                                    556,
                                    565,
                                    554,
                                    566,
                                    618,
                                    394,
                                    619
                                ],
                                "text": "the",
                                "confidence": 0.617
                            },
                            {
                                "boundingBox": [
                                    647,
                                    553,
                                    808,
                                    552,
                                    809,
                                    617,
                                    648,
                                    617
                                ],
                                "text": "data",
                                "confidence": 0.888
                            },
                            {
                                "boundingBox": [
                                    845,
                                    552,
                                    989,
                                    551,
                                    990,
                                    617,
                                    846,
                                    617
                                ],
                                "text": "safe",
                                "confidence": 0.559
                            },
                            {
                                "boundingBox": [
                                    1001,
                                    551,
                                    1117,
                                    551,
                                    1117,
                                    617,
                                    1002,
                                    617
                                ],
                                "text": "of",
                                "confidence": 0.559
                            },
                            {
                                "boundingBox": [
                                    1133,
                                    551,
                                    1396,
                                    553,
                                    1397,
                                    618,
                                    1134,
                                    617
                                ],
                                "text": "ensuring",
                                "confidence": 0.756
                            },
                            {
                                "boundingBox": [
                                    1454,
                                    554,
                                    1684,
                                    558,
                                    1685,
                                    620,
                                    1454,
                                    618
                                ],
                                "text": "storage",
                                "confidence": 0.941
                            },
                            {
                                "boundingBox": [
                                    1697,
                                    558,
                                    1783,
                                    560,
                                    1783,
                                    621,
                                    1697,
                                    620
                                ],
                                "text": "of",
                                "confidence": 0.69
                            },
                            {
                                "boundingBox": [
                                    1804,
                                    560,
                                    1927,
                                    563,
                                    1927,
                                    622,
                                    1804,
                                    621
                                ],
                                "text": "data",
                                "confidence": 0.958
                            },
                            {
                                "boundingBox": [
                                    1940,
                                    563,
                                    2034,
                                    566,
                                    2034,
                                    624,
                                    1939,
                                    622
                                ],
                                "text": "is",
                                "confidence": 0.986
                            },
                            {
                                "boundingBox": [
                                    2071,
                                    567,
                                    2162,
                                    569,
                                    2161,
                                    625,
                                    2071,
                                    624
                                ],
                                "text": "not",
                                "confidence": 0.985
                            }
                        ]
                    },
                    {
                        "boundingBox": [
                            527,
                            620,
                            961,
                            603,
                            963,
                            662,
                            529,
                            676
                        ],
                        "text": "vulnerable :",
                        "words": [
                            {
                                "boundingBox": [
                                    541,
                                    626,
                                    900,
                                    608,
                                    903,
                                    666,
                                    544,
                                    676
                                ],
                                "text": "vulnerable",
                                "confidence": 0.643
                            },
                            {
                                "boundingBox": [
                                    942,
                                    605,
                                    962,
                                    603,
                                    964,
                                    664,
                                    945,
                                    664
                                ],
                                "text": ":",
                                "confidence": 0.949
                            }
                        ]
                    },
                    {
                        "boundingBox": [
                            292,
                            683,
                            2261,
                            684,
                            2261,
                            766,
                            292,
                            765
                        ],
                        "text": ". Encryption - Enoypting the data can s guide out",
                        "words": [
                            {
                                "boundingBox": [
                                    292,
                                    690,
                                    358,
                                    689,
                                    359,
                                    765,
                                    294,
                                    766
                                ],
                                "text": ".",
                                "confidence": 0.981
                            },
                            {
                                "boundingBox": [
                                    388,
                                    689,
                                    720,
                                    685,
                                    721,
                                    758,
                                    390,
                                    765
                                ],
                                "text": "Encryption",
                                "confidence": 0.559
                            },
                            {
                                "boundingBox": [
                                    735,
                                    685,
                                    811,
                                    684,
                                    812,
                                    757,
                                    737,
                                    758
                                ],
                                "text": "-",
                                "confidence": 0.981
                            },
                            {
                                "boundingBox": [
                                    856,
                                    684,
                                    1223,
                                    684,
                                    1224,
                                    754,
                                    857,
                                    756
                                ],
                                "text": "Enoypting",
                                "confidence": 0.737
                            },
                            {
                                "boundingBox": [
                                    1239,
                                    684,
                                    1400,
                                    685,
                                    1400,
                                    753,
                                    1239,
                                    754
                                ],
                                "text": "the",
                                "confidence": 0.975
                            },
                            {
                                "boundingBox": [
                                    1445,
                                    685,
                                    1631,
                                    687,
                                    1632,
                                    754,
                                    1446,
                                    753
                                ],
                                "text": "data",
                                "confidence": 0.979
                            },
                            {
                                "boundingBox": [
                                    1656,
                                    687,
                                    1812,
                                    690,
                                    1813,
                                    755,
                                    1657,
                                    754
                                ],
                                "text": "can",
                                "confidence": 0.985
                            },
                            {
                                "boundingBox": [
                                    1837,
                                    690,
                                    1913,
                                    691,
                                    1913,
                                    756,
                                    1838,
                                    755
                                ],
                                "text": "s",
                                "confidence": 0.559
                            },
                            {
                                "boundingBox": [
                                    1948,
                                    692,
                                    2144,
                                    696,
                                    2144,
                                    759,
                                    1948,
                                    756
                                ],
                                "text": "guide",
                                "confidence": 0.559
                            },
                            {
                                "boundingBox": [
                                    2160,
                                    697,
                                    2260,
                                    699,
                                    2260,
                                    761,
                                    2159,
                                    760
                                ],
                                "text": "out",
                                "confidence": 0.986
                            }
                        ]
                    },
                    {
                        "boundingBox": [
                            826,
                            783,
                            2206,
                            774,
                            2206,
                            833,
                            826,
                            849
                        ],
                        "text": "the possibility of unauthorized use.",
                        "words": [
                            {
                                "boundingBox": [
                                    841,
                                    784,
                                    988,
                                    782,
                                    986,
                                    849,
                                    839,
                                    850
                                ],
                                "text": "the",
                                "confidence": 0.979
                            },
                            {
                                "boundingBox": [
                                    1018,
                                    782,
                                    1376,
                                    778,
                                    1374,
                                    844,
                                    1016,
                                    849
                                ],
                                "text": "possibility",
                                "confidence": 0.895
                            },
                            {
                                "boundingBox": [
                                    1410,
                                    778,
                                    1505,
                                    777,
                                    1504,
                                    842,
                                    1409,
                                    844
                                ],
                                "text": "of",
                                "confidence": 0.979
                            },
                            {
                                "boundingBox": [
                                    1570,
                                    776,
                                    2005,
                                    775,
                                    2005,
                                    833,
                                    1569,
                                    841
                                ],
                                "text": "unauthorized",
                                "confidence": 0.719
                            },
                            {
                                "boundingBox": [
                                    2036,
                                    775,
                                    2204,
                                    775,
                                    2203,
                                    829,
                                    2035,
                                    832
                                ],
                                "text": "use.",
                                "confidence": 0.652
                            }
                        ]
                    },
                    {
                        "boundingBox": [
                            780,
                            865,
                            2322,
                            844,
                            2323,
                            905,
                            781,
                            930
                        ],
                        "text": "Only authorized users can decuppt the data",
                        "words": [
                            {
                                "boundingBox": [
                                    802,
                                    866,
                                    972,
                                    864,
                                    974,
                                    929,
                                    804,
                                    930
                                ],
                                "text": "Only",
                                "confidence": 0.825
                            },
                            {
                                "boundingBox": [
                                    1015,
                                    864,
                                    1377,
                                    860,
                                    1377,
                                    924,
                                    1016,
                                    929
                                ],
                                "text": "authorized",
                                "confidence": 0.559
                            },
                            {
                                "boundingBox": [
                                    1432,
                                    859,
                                    1624,
                                    856,
                                    1624,
                                    919,
                                    1433,
                                    923
                                ],
                                "text": "users",
                                "confidence": 0.699
                            },
                            {
                                "boundingBox": [
                                    1641,
                                    856,
                                    1777,
                                    854,
                                    1777,
                                    915,
                                    1641,
                                    918
                                ],
                                "text": "can",
                                "confidence": 0.986
                            },
                            {
                                "boundingBox": [
                                    1816,
                                    853,
                                    2088,
                                    849,
                                    2087,
                                    906,
                                    1815,
                                    914
                                ],
                                "text": "decuppt",
                                "confidence": 0.765
                            },
                            {
                                "boundingBox": [
                                    2101,
                                    849,
                                    2229,
                                    846,
                                    2227,
                                    901,
                                    2099,
                                    905
                                ],
                                "text": "the",
                                "confidence": 0.975
                            },
                            {
                                "boundingBox": [
                                    2242,
                                    846,
                                    2323,
                                    844,
                                    2320,
                                    897,
                                    2240,
                                    900
                                ],
                                "text": "data",
                                "confidence": 0.559
                            }
                        ]
                    },
                    {
                        "boundingBox": [
                            254,
                            977,
                            2298,
                            975,
                            2298,
                            1056,
                            254,
                            1062
                        ],
                        "text": ". Authentication A proper && well secured authentication",
                        "words": [
                            {
                                "boundingBox": [
                                    254,
                                    987,
                                    320,
                                    986,
                                    321,
                                    1062,
                                    256,
                                    1063
                                ],
                                "text": ".",
                                "confidence": 0.984
                            },
                            {
                                "boundingBox": [
                                    365,
                                    985,
                                    895,
                                    977,
                                    896,
                                    1045,
                                    367,
                                    1060
                                ],
                                "text": "Authentication",
                                "confidence": 0.751
                            },
                            {
                                "boundingBox": [
                                    971,
                                    976,
                                    1047,
                                    976,
                                    1047,
                                    1042,
                                    972,
                                    1044
                                ],
                                "text": "A",
                                "confidence": 0.986
                            },
                            {
                                "boundingBox": [
                                    1072,
                                    975,
                                    1315,
                                    975,
                                    1315,
                                    1040,
                                    1073,
                                    1042
                                ],
                                "text": "proper",
                                "confidence": 0.825
                            },
                            {
                                "boundingBox": [
                                    1330,
                                    975,
                                    1421,
                                    975,
                                    1421,
                                    1039,
                                    1330,
                                    1040
                                ],
                                "text": "&&",
                                "confidence": 0.559
                            },
                            {
                                "boundingBox": [
                                    1471,
                                    976,
                                    1608,
                                    977,
                                    1607,
                                    1039,
                                    1471,
                                    1039
                                ],
                                "text": "well",
                                "confidence": 0.985
                            },
                            {
                                "boundingBox": [
                                    1623,
                                    977,
                                    1900,
                                    980,
                                    1900,
                                    1042,
                                    1622,
                                    1039
                                ],
                                "text": "secured",
                                "confidence": 0.559
                            },
                            {
                                "boundingBox": [
                                    1941,
                                    981,
                                    2299,
                                    989,
                                    2298,
                                    1049,
                                    1940,
                                    1042
                                ],
                                "text": "authentication",
                                "confidence": 0.667
                            }
                        ]
                    },
                    {
                        "boundingBox": [
                            888,
                            1072,
                            2094,
                            1065,
                            2095,
                            1124,
                            889,
                            1136
                        ],
                        "text": "can prevent unauthorized access",
                        "words": [
                            {
                                "boundingBox": [
                                    904,
                                    1080,
                                    1038,
                                    1075,
                                    1039,
                                    1135,
                                    905,
                                    1137
                                ],
                                "text": "can",
                                "confidence": 0.986
                            },
                            {
                                "boundingBox": [
                                    1102,
                                    1073,
                                    1353,
                                    1068,
                                    1353,
                                    1130,
                                    1103,
                                    1134
                                ],
                                "text": "prevent",
                                "confidence": 0.828
                            },
                            {
                                "boundingBox": [
                                    1417,
                                    1067,
                                    1844,
                                    1066,
                                    1842,
                                    1126,
                                    1416,
                                    1129
                                ],
                                "text": "unauthorized",
                                "confidence": 0.662
                            },
                            {
                                "boundingBox": [
                                    1911,
                                    1066,
                                    2095,
                                    1069,
                                    2093,
                                    1125,
                                    1910,
                                    1126
                                ],
                                "text": "access",
                                "confidence": 0.568
                            }
                        ]
                    },
                    {
                        "boundingBox": [
                            189,
                            1159,
                            1668,
                            1142,
                            1669,
                            1205,
                            191,
                            1234
                        ],
                        "text": ". Authorization - A Well secured authorization",
                        "words": [
                            {
                                "boundingBox": [
                                    190,
                                    1164,
                                    256,
                                    1162,
                                    263,
                                    1232,
                                    198,
                                    1235
                                ],
                                "text": ".",
                                "confidence": 0.981
                            },
                            {
                                "boundingBox": [
                                    289,
                                    1161,
                                    662,
                                    1150,
                                    667,
                                    1212,
                                    296,
                                    1230
                                ],
                                "text": "Authorization",
                                "confidence": 0.564
                            },
                            {
                                "boundingBox": [
                                    676,
                                    1150,
                                    747,
                                    1148,
                                    752,
                                    1209,
                                    681,
                                    1212
                                ],
                                "text": "-",
                                "confidence": 0.984
                            },
                            {
                                "boundingBox": [
                                    775,
                                    1148,
                                    846,
                                    1147,
                                    850,
                                    1206,
                                    780,
                                    1208
                                ],
                                "text": "A",
                                "confidence": 0.791
                            },
                            {
                                "boundingBox": [
                                    865,
                                    1146,
                                    988,
                                    1145,
                                    991,
                                    1202,
                                    869,
                                    1205
                                ],
                                "text": "Well",
                                "confidence": 0.985
                            },
                            {
                                "boundingBox": [
                                    1002,
                                    1145,
                                    1261,
                                    1143,
                                    1263,
                                    1197,
                                    1005,
                                    1202
                                ],
                                "text": "secured",
                                "confidence": 0.684
                            },
                            {
                                "boundingBox": [
                                    1294,
                                    1143,
                                    1667,
                                    1145,
                                    1667,
                                    1197,
                                    1296,
                                    1197
                                ],
                                "text": "authorization",
                                "confidence": 0.586
                            }
                        ]
                    },
                    {
                        "boundingBox": [
                            1695,
                            1142,
                            2300,
                            1142,
                            2300,
                            1199,
                            1695,
                            1199
                        ],
                        "text": "& makes sure only",
                        "words": [
                            {
                                "boundingBox": [
                                    1737,
                                    1146,
                                    1785,
                                    1146,
                                    1785,
                                    1197,
                                    1738,
                                    1196
                                ],
                                "text": "&",
                                "confidence": 0.559
                            },
                            {
                                "boundingBox": [
                                    1854,
                                    1146,
                                    2013,
                                    1146,
                                    2012,
                                    1200,
                                    1854,
                                    1199
                                ],
                                "text": "makes",
                                "confidence": 0.968
                            },
                            {
                                "boundingBox": [
                                    2042,
                                    1146,
                                    2200,
                                    1144,
                                    2199,
                                    1200,
                                    2041,
                                    1200
                                ],
                                "text": "sure",
                                "confidence": 0.652
                            },
                            {
                                "boundingBox": [
                                    2216,
                                    1144,
                                    2299,
                                    1143,
                                    2297,
                                    1199,
                                    2215,
                                    1200
                                ],
                                "text": "only",
                                "confidence": 0.929
                            }
                        ]
                    },
                    {
                        "boundingBox": [
                            780,
                            1207,
                            2282,
                            1220,
                            2282,
                            1285,
                            780,
                            1263
                        ],
                        "text": "entitled usere are given access to the-data.",
                        "words": [
                            {
                                "boundingBox": [
                                    801,
                                    1211,
                                    1067,
                                    1208,
                                    1067,
                                    1262,
                                    801,
                                    1262
                                ],
                                "text": "entitled",
                                "confidence": 0.872
                            },
                            {
                                "boundingBox": [
                                    1111,
                                    1208,
                                    1257,
                                    1207,
                                    1257,
                                    1263,
                                    1111,
                                    1262
                                ],
                                "text": "usere",
                                "confidence": 0.979
                            },
                            {
                                "boundingBox": [
                                    1274,
                                    1207,
                                    1397,
                                    1208,
                                    1397,
                                    1264,
                                    1274,
                                    1263
                                ],
                                "text": "are",
                                "confidence": 0.98
                            },
                            {
                                "boundingBox": [
                                    1424,
                                    1208,
                                    1580,
                                    1210,
                                    1580,
                                    1267,
                                    1423,
                                    1264
                                ],
                                "text": "given",
                                "confidence": 0.973
                            },
                            {
                                "boundingBox": [
                                    1624,
                                    1211,
                                    1830,
                                    1215,
                                    1829,
                                    1272,
                                    1623,
                                    1268
                                ],
                                "text": "access",
                                "confidence": 0.979
                            },
                            {
                                "boundingBox": [
                                    1847,
                                    1216,
                                    1924,
                                    1218,
                                    1922,
                                    1274,
                                    1846,
                                    1272
                                ],
                                "text": "to",
                                "confidence": 0.986
                            },
                            {
                                "boundingBox": [
                                    1934,
                                    1218,
                                    2283,
                                    1232,
                                    2281,
                                    1286,
                                    1932,
                                    1275
                                ],
                                "text": "the-data.",
                                "confidence": 0.913
                            }
                        ]
                    }
                ]
            }
        ]
    }
}